anyrpc/__init__.py
anyrpc/serve.py
anyrpc/stub.py
anyrpc/test_client.py
anyrpc-0.0.1.dist-info/METADATA
anyrpc-0.0.1.dist-info/WHEEL
anyrpc-0.0.1.dist-info/top_level.txt
anyrpc-0.0.1.dist-info/RECORD
