Metadata-Version: 2.1
Name: anyrpc
Version: 0.0.1
Summary: Python implementation of any-rpc
Home-page: https://github.com/fuchen/any-rpc-py
Author: fuchen
Author-email: ink.pad@163.com
License: UNKNOWN
Platform: UNKNOWN
